README.md
setup.py
wanakana/__init__.py
wanakana/common.py
wanakana/constants.py
wanakana/japanese.py
wanakana/version.py
wanakana/utils/__init__.py
wanakana/utils/common.py
wanakana/utils/english.py
wanakana/utils/kana_mapping.py
wanakana/utils/kana_to_romaji_map.py
wanakana/utils/romaji_to_kana_map.py
wanakana/utils/japanese/__init__.py
wanakana/utils/japanese/common.py
wanakana/utils/japanese/hiragana.py
wanakana/utils/japanese/hiragana_to_katakana.py
wanakana/utils/japanese/kanji.py
wanakana/utils/japanese/katakana.py
wanakana/utils/japanese/katakana_to_hiragana.py
wanakana_python.egg-info/PKG-INFO
wanakana_python.egg-info/SOURCES.txt
wanakana_python.egg-info/dependency_links.txt
wanakana_python.egg-info/top_level.txt