Metadata-Version: 2.1
Name: wanakana-python
Version: 1.2.2
Summary: A port of WanaKana, a JS library by Tofugu
Home-page: https://github.com/starwort/wanakana
Author: starwort
License: MPL-2.0
Platform: UNKNOWN
Classifier: Programming Language :: Python :: 3.6
